sneval/__init__.py
sneval/analyze.py
sneval/dataset.py
sneval/evaluate.py
sneval/metrics/__init__.py
sneval/metrics/base.py
sneval/metrics/basic/__init__.py
sneval/metrics/basic/base.py
sneval/metrics/basic/metrics.py
sneval/metrics/compare/__init__.py
sneval/metrics/compare/base.py
sneval/metrics/compare/metrics.py
sneval/utils/__init__.py
sneval/utils/io.py
smartnoise_eval-0.3.1.dist-info/METADATA
smartnoise_eval-0.3.1.dist-info/WHEEL
smartnoise_eval-0.3.1.dist-info/RECORD
