Metadata-Version: 2.3
Name: smartnoise-eval
Version: 0.3.1
Summary: Evaluation of differentially private tabular data
License: MIT
Author: SmartNoise Team
Author-email: smartnoise@opendp.org
Requires-Python: >=3.9,<3.13
Classifier: License :: OSI Approved :: MIT License
Classifier: Programming Language :: Python :: 3
Classifier: Programming Language :: Python :: 3.9
Classifier: Programming Language :: Python :: 3.10
Classifier: Programming Language :: Python :: 3.11
Classifier: Programming Language :: Python :: 3.12
Requires-Dist: numpy (>=1.26.1,<2.0.0)
Requires-Dist: pyspark (>=3.5.0,<4.0.0)
Project-URL: Homepage, https://smartnoise.org
Project-URL: Repository, https://github.com/opendp/smartnoise-sdk
